<?xml version="1.0" encoding="UTF-8" ?>
<!DOCTYPE mapper
        PUBLIC "-//mybatis.org//DTD Mapper 3.0//EN"
        "http://mybatis.org/dtd/mybatis-3-mapper.dtd">
<mapper namespace="com.leetcode.leetcode_ai.mapper.RecommendationMapper">

    <resultMap id="problemResultMap" type="com.leetcode.leetcode_ai.entity.ProblemEntity">
        <id property="id" column="id"/>
        <result property="title" column="title"/>
        <result property="difficulty" column="difficulty"/>
        <result property="status" column="status"/>
        <result property="createdAt" column="created_at"/>
        <result property="updatedAt" column="updated_at"/>
    </resultMap>

    <select id="findWrongSeeds" resultType="com.leetcode.leetcode_ai.mapper.row.WrongSeedRow">
        select wq.problem_id as problemId,
               p.difficulty as difficulty,
               wq.last_wrong_type as lastWrongType,
               wq.wrong_count as wrongCount
        from wrong_questions wq
                 join problems p on p.id = wq.problem_id
        where wq.user_id = #{userId}
        order by wq.wrong_count desc, wq.last_wrong_at desc
        limit #{limit}
    </select>

    <select id="findTagIdsByProblemIds" resultType="long">
        select distinct pt.tag_id
        from problem_tags pt
        where pt.problem_id in
        <foreach collection="problemIds" item="id" open="(" separator="," close=")">
            #{id}
        </foreach>
    </select>

    <select id="findCandidatesByTags" resultMap="problemResultMap">
        select p.id, p.title, p.difficulty, p.status, p.created_at, p.updated_at, p.accepted_count
        from problems p
                 join problem_tags pt on pt.problem_id = p.id
        where p.status = 1
          and pt.tag_id in
          <foreach collection="tagIds" item="tagId" open="(" separator="," close=")">
              #{tagId}
          </foreach>
          and not exists (
            select 1 from submissions s where s.user_id = #{userId} and s.problem_id = p.id
          )
          <if test="excludeProblemIds != null and excludeProblemIds.size() > 0">
              and p.id not in
              <foreach collection="excludeProblemIds" item="pid" open="(" separator="," close=")">
                  #{pid}
              </foreach>
          </if>
        group by p.id, p.title, p.difficulty, p.status, p.created_at, p.updated_at, p.accepted_count
        order by p.accepted_count asc, p.id desc
        limit #{limit}
    </select>

    <select id="findCandidatesByDifficulty" resultMap="problemResultMap">
        select p.id, p.title, p.difficulty, p.status, p.created_at, p.updated_at
        from problems p
        where p.status = 1
          and p.difficulty = #{difficulty}
          and not exists (
            select 1 from submissions s where s.user_id = #{userId} and s.problem_id = p.id
          )
          <if test="excludeProblemIds != null and excludeProblemIds.size() > 0">
              and p.id not in
              <foreach collection="excludeProblemIds" item="pid" open="(" separator="," close=")">
                  #{pid}
              </foreach>
          </if>
        order by p.accepted_count asc, p.id desc
        limit #{limit}
    </select>

    <insert id="insertRecommendationRecord">
        insert into recommendation_records (
            user_id, trigger_source, trigger_ref_id, resource_type, resource_id, problem_id, reason_text, ai_source, ai_model, score, recommended_at
        )
        values (
            #{userId}, #{triggerSource}, #{triggerRefId}, #{resourceType}, #{resourceId}, #{problemId}, #{reasonText}, #{aiSource}, #{aiModel}, #{score}, now()
        )
    </insert>

    <select id="countRecordsByUserId" resultType="long">
        select count(1)
        from recommendation_records
        where user_id = #{userId}
    </select>

    <select id="findRecordPageByUserId" resultType="com.leetcode.leetcode_ai.vo.RecommendationRecordItemVo">
        select rr.id,
               rr.trigger_source as triggerSource,
               rr.trigger_ref_id as triggerRefId,
               rr.resource_type as resourceType,
               rr.resource_id as resourceId,
               rr.problem_id as problemId,
               p.title as problemTitle,
               p.difficulty as difficulty,
               rr.reason_text as reasonText,
               rr.ai_source as aiSource,
               rr.ai_model as aiModel,
               rr.score,
               rr.recommended_at as recommendedAt
        from recommendation_records rr
                 left join problems p on p.id = rr.problem_id
        where rr.user_id = #{userId}
        order by rr.recommended_at desc, rr.id desc
        limit #{size} offset #{offset}
    </select>

    <delete id="pruneUserRecordsKeepLatest">
        delete rr
        from recommendation_records rr
                 join (
            select id
            from recommendation_records
            where user_id = #{userId}
            order by recommended_at desc, id desc
            limit 18446744073709551615 offset #{keep}
        ) old on old.id = rr.id
        where rr.user_id = #{userId}
    </delete>

</mapper>
